spans/__init__.py
spans/_compat.py
spans/_utils.py
spans/settypes.py
spans/types.py
Spans-1.1.1.dist-info/LICENSE
Spans-1.1.1.dist-info/METADATA
Spans-1.1.1.dist-info/WHEEL
Spans-1.1.1.dist-info/top_level.txt
Spans-1.1.1.dist-info/RECORD
