Metadata-Version: 2.1
Name: Spans
Version: 1.1.1
Summary: Continuous set support for Python
Home-page: https://www.github.com/runfalk/spans
Author: Andreas Runfalk
Author-email: andreas@runfalk.se
License: MIT
Platform: UNKNOWN
Classifier: Development Status :: 5 - Production/Stable
Classifier: Intended Audience :: Developers
Classifier: License :: OSI Approved :: MIT License
Classifier: Programming Language :: Python
Classifier: Programming Language :: Python :: 2
Classifier: Programming Language :: Python :: 3
Classifier: Programming Language :: Python :: 2.7
Classifier: Programming Language :: Python :: 3.4
Classifier: Programming Language :: Python :: 3.5
Classifier: Programming Language :: Python :: 3.6
Classifier: Programming Language :: Python :: 3.7
Classifier: Programming Language :: Python :: 3.8
Classifier: Programming Language :: Python :: 3.9
Classifier: Programming Language :: Python :: Implementation :: CPython
Classifier: Programming Language :: Python :: Implementation :: PyPy
Classifier: Topic :: Utilities
Provides-Extra: dev
Requires-Dist: codecov ; extra == 'dev'
Requires-Dist: pytest (>=3.0) ; extra == 'dev'
Requires-Dist: pytest-cov ; extra == 'dev'
Requires-Dist: twine ; extra == 'dev'
Requires-Dist: Sphinx ; (python_version!='3.3') and extra == 'dev'
Requires-Dist: sphinx-rtd-theme ; (python_version!='3.3') and extra == 'dev'
